pylylabel-4.0.0.dist-info/METADATA
pylylabel-4.0.0.dist-info/WHEEL
pylylabel/__init__.py
pylylabel/test.py
pylylabel/pylylabel.cpython-38-darwin.so
pylylabel-4.0.0.dist-info/RECORD
