Metadata-Version: 2.1
Name: pylylabel
Version: 4.0.0
Requires-Dist: Shapely>=1.6.0
Summary: A Rust implementation of the Polylabel algorithm for finding optimum polygon label positions, with Python binding.
Keywords: geo,polylabel,gis
Author: Stephan Hügel <urschrei@gmail.com>, Andy Wang <cbeuw.andy@gmail.com>
Author-email: Stephan Hügel <urschrei@gmail.com>, Andy Wang <cbeuw.andy@gmail.com>
License: MIT
